Metadata-Version: 2.1
Name: brainome-linux-python3.7
Version: 1.6.82
Summary: Brainome Table Compiler
Home-page: https://github.com/brainome/examples
Author: Brainome, Inc
Author-email: support@brainome.ai
License: BSD
Platform: UNKNOWN
Classifier: Development Status :: 5 - Production/Stable
Classifier: Environment :: Console
Classifier: Environment :: GPU :: NVIDIA CUDA
Classifier: Intended Audience :: Science/Research
Classifier: Intended Audience :: Developers
Classifier: Intended Audience :: Education
Classifier: License :: OSI Approved :: BSD License
Classifier: Operating System :: POSIX :: Linux
Classifier: Programming Language :: Python :: 3 :: Only
Classifier: Topic :: Scientific/Engineering :: Artificial Intelligence
Classifier: Topic :: Utilities
License-File: LICENSE
Requires-Dist: requests
Requires-Dist: numpy (>=1.20.0)
Requires-Dist: scikit-learn (>=0.22.1)
Requires-Dist: torch (>=1.4.0)
Requires-Dist: Jinja2 (>=3.0.0)
Requires-Dist: xgboost (==1.3.3)
